fm_training_estimator/__init__.py
fm_training_estimator/_version.py
fm_training_estimator/config/__init__.py
fm_training_estimator/config/arguments.py
fm_training_estimator/config/parser.py
fm_training_estimator/config/test_parser.py
fm_training_estimator/config/test_utils.py
fm_training_estimator/config/utils.py
fm_training_estimator/config/test_configs/config1.json
fm_training_estimator/config/test_configs/config2.json
fm_training_estimator/config/test_configs/config3.json
fm_training_estimator/config/test_configs/config4.json
fm_training_estimator/data/README.md
fm_training_estimator/data/__init__.py
fm_training_estimator/data/manager.py
fm_training_estimator/memory/__init__.py
fm_training_estimator/memory/fsdp/__init__.py
fm_training_estimator/memory/fsdp/fsdp.py
fm_training_estimator/memory/fsdp/test_fsdp.py
fm_training_estimator/memory/full/README.md
fm_training_estimator/memory/full/__init__.py
fm_training_estimator/memory/full/full.py
fm_training_estimator/memory/full/test_full.py
fm_training_estimator/memory/hybrid/README.md
fm_training_estimator/memory/hybrid/__init__.py
fm_training_estimator/memory/hybrid/hybrid.py
fm_training_estimator/memory/hybrid/hybrid_test.py
fm_training_estimator/memory/lora/__init__.py
fm_training_estimator/memory/lora/hybrid.py
fm_training_estimator/memory/lora/lora.py
fm_training_estimator/memory/lora/test_lora.py
fm_training_estimator/memory/qlora/__init__.py
fm_training_estimator/memory/qlora/hybrid.py
fm_training_estimator/memory/qlora/qlora.py
fm_training_estimator/memory/qlora/test_qlora.py
fm_training_estimator/regressor/README.md
fm_training_estimator/regressor/__init__.py
fm_training_estimator/regressor/dispatch.py
fm_training_estimator/regressor/linear/__init__.py
fm_training_estimator/regressor/linear/linear.py
fm_training_estimator/regressor/linear/train.py
fm_training_estimator/regressor/lookup/__init__.py
fm_training_estimator/regressor/lookup/lookup.py
fm_training_estimator/regressor/lookup/test_lookup.py
fm_training_estimator-0.1.0.dist-info/LICENSE
fm_training_estimator-0.1.0.dist-info/METADATA
fm_training_estimator-0.1.0.dist-info/WHEEL
fm_training_estimator-0.1.0.dist-info/top_level.txt
fm_training_estimator-0.1.0.dist-info/RECORD
