Metadata-Version: 2.2
Name: fm_training_estimator
Version: 0.1.0
Summary: A package of Estimators for Large Language Model Training.
Author-email: Angel Luu <angel.luu@us.ibm.com>, Chander Govindarajan <mail@chandergovind.org>
License: Apache-2.0
Project-URL: Source, https://github.com/foundation-model-stack/fm-training-estimator
Classifier: Programming Language :: Python :: 3
Classifier: License :: OSI Approved :: Apache Software License
Classifier: Operating System :: OS Independent
Requires-Python: >=3.8
License-File: LICENSE
Requires-Dist: tox
Requires-Dist: pre-commit
Requires-Dist: transformers
Requires-Dist: peft
Requires-Dist: setuptools
Requires-Dist: fire
Requires-Dist: pandas
Requires-Dist: xgboost
Requires-Dist: scikit-learn<1.6.0
Requires-Dist: gradio
Requires-Dist: datasets
Requires-Dist: dataclass-wizard
Requires-Dist: uvicorn
Provides-Extra: dev-docs
Requires-Dist: sphinx<8.0,>=4.0.2; extra == "dev-docs"
Requires-Dist: sphinx-autoapi>=2.1.0; extra == "dev-docs"
Requires-Dist: sphinx-rtd-theme<2.1.0,>=1.2.1; extra == "dev-docs"
